{"dwell_times": [{"arr_dt": "1452661149", "direction": "0", "dep_dt": "1452661275", "route_id": "Red", "dwell_time_sec": "126"}, {"arr_dt": "1452661389", "direction": "0", "dep_dt": "1452661441", "route_id": "Red", "dwell_time_sec": "52"}, {"arr_dt": "1452661681", "direction": "0", "dep_dt": "1452661736", "route_id": "Red", "dwell_time_sec": "55"}, {"arr_dt": "1452662095", "direction": "0", "dep_dt": "1452662157", "route_id": "Red", "dwell_time_sec": "62"}, {"arr_dt": "1452662396", "direction": "0", "dep_dt": "1452662488", "route_id": "Red", "dwell_time_sec": "92"}, {"arr_dt": "1452662860", "direction": "0", "dep_dt": "1452662924", "route_id": "Red", "dwell_time_sec": "64"}, {"arr_dt": "1452663429", "direction": "0", "dep_dt": "1452663489", "route_id": "Red", "dwell_time_sec": "60"}, {"arr_dt": "1452664134", "direction": "0", "dep_dt": "1452666381", "route_id": "Red", "dwell_time_sec": "2247"}, {"arr_dt": "1452681238", "direction": "0", "dep_dt": "1452681293", "route_id": "Red", "dwell_time_sec": "55"}, {"arr_dt": "1452681750", "direction": "0", "dep_dt": "1452681844", "route_id": "Red", "dwell_time_sec": "94"}, {"arr_dt": "1452682032", "direction": "0", "dep_dt": "1452682089", "route_id": "Red", "dwell_time_sec": "57"}, {"arr_dt": "1452682613", "direction": "0", "dep_dt": "1452682667", "route_id": "Red", "dwell_time_sec": "54"}, {"arr_dt": "1452683032", "direction": "0", "dep_dt": "1452683089", "route_id": "Red", "dwell_time_sec": "57"}, {"arr_dt": "1452683621", "direction": "0", "dep_dt": "1452683676", "route_id": "Red", "dwell_time_sec": "55"}, {"arr_dt": "1452683976", "direction": "0", "dep_dt": "1452684030", "route_id": "Red", "dwell_time_sec": "54"}, {"arr_dt": "1452684408", "direction": "0", "dep_dt": "1452684470", "route_id": "Red", "dwell_time_sec": "62"}, {"arr_dt": "1452684725", "direction": "0", "dep_dt": "1452684781", "route_id": "Red", "dwell_time_sec": "56"}, {"arr_dt": "1452685293", "direction": "0", "dep_dt": "1452685364", "route_id": "Red", "dwell_time_sec": "71"}, {"arr_dt": "1452685536", "direction": "0", "dep_dt": "1452685595", "route_id": "Red", "dwell_time_sec": "59"}, {"arr_dt": "1452685959", "direction": "0", "dep_dt": "1452686028", "route_id": "Red", "dwell_time_sec": "69"}, {"arr_dt": "1452686365", "direction": "0", "dep_dt": "1452686437", "route_id": "Red", "dwell_time_sec": "72"}, {"arr_dt": "1452687082", "direction": "0", "dep_dt": "1452687175", "route_id": "Red", "dwell_time_sec": "93"}, {"arr_dt": "1452687271", "direction": "0", "dep_dt": "1452687352", "route_id": "Red", "dwell_time_sec": "81"}, {"arr_dt": "1452687501", "direction": "0", "dep_dt": "1452687589", "route_id": "Red", "dwell_time_sec": "88"}, {"arr_dt": "1452687688", "direction": "0", "dep_dt": "1452687766", "route_id": "Red", "dwell_time_sec": "78"}, {"arr_dt": "1452688117", "direction": "0", "dep_dt": "1452688222", "route_id": "Red", "dwell_time_sec": "105"}, {"arr_dt": "1452688331", "direction": "0", "dep_dt": "1452688393", "route_id": "Red", "dwell_time_sec": "62"}, {"arr_dt": "1452688512", "direction": "0", "dep_dt": "1452688579", "route_id": "Red", "dwell_time_sec": "67"}, {"arr_dt": "1452688763", "direction": "0", "dep_dt": "1452688852", "route_id": "Red", "dwell_time_sec": "89"}, {"arr_dt": "1452689084", "direction": "0", "dep_dt": "1452689166", "route_id": "Red", "dwell_time_sec": "82"}, {"arr_dt": "1452689283", "direction": "0", "dep_dt": "1452689363", "route_id": "Red", "dwell_time_sec": "80"}, {"arr_dt": "1452689469", "direction": "0", "dep_dt": "1452689583", "route_id": "Red", "dwell_time_sec": "114"}, {"arr_dt": "1452689682", "direction": "0", "dep_dt": "1452689811", "route_id": "Red", "dwell_time_sec": "129"}, {"arr_dt": "1452689920", "direction": "0", "dep_dt": "1452690006", "route_id": "Red", "dwell_time_sec": "86"}, {"arr_dt": "1452690097", "direction": "0", "dep_dt": "1452690175", "route_id": "Red", "dwell_time_sec": "78"}, {"arr_dt": "1452690300", "direction": "0", "dep_dt": "1452690379", "route_id": "Red", "dwell_time_sec": "79"}, {"arr_dt": "1452690507", "direction": "0", "dep_dt": "1452690658", "route_id": "Red", "dwell_time_sec": "151"}, {"arr_dt": "1452690758", "direction": "0", "dep_dt": "1452690881", "route_id": "Red", "dwell_time_sec": "123"}, {"arr_dt": "1452690967", "direction": "0", "dep_dt": "1452691059", "route_id": "Red", "dwell_time_sec": "92"}, {"arr_dt": "1452691197", "direction": "0", "dep_dt": "1452691292", "route_id": "Red", "dwell_time_sec": "95"}, {"arr_dt": "1452691409", "direction": "0", "dep_dt": "1452691488", "route_id": "Red", "dwell_time_sec": "79"}, {"arr_dt": "1452691607", "direction": "0", "dep_dt": "1452691718", "route_id": "Red", "dwell_time_sec": "111"}, {"arr_dt": "1452691839", "direction": "0", "dep_dt": "1452691941", "route_id": "Red", "dwell_time_sec": "102"}, {"arr_dt": "1452692048", "direction": "0", "dep_dt": "1452692166", "route_id": "Red", "dwell_time_sec": "118"}, {"arr_dt": "1452692252", "direction": "0", "dep_dt": "1452692362", "route_id": "Red", "dwell_time_sec": "110"}, {"arr_dt": "1452692682", "direction": "0", "dep_dt": "1452692808", "route_id": "Red", "dwell_time_sec": "126"}, {"arr_dt": "1452692931", "direction": "0", "dep_dt": "1452693071", "route_id": "Red", "dwell_time_sec": "140"}, {"arr_dt": "1452693426", "direction": "0", "dep_dt": "1452693567", "route_id": "Red", "dwell_time_sec": "141"}, {"arr_dt": "1452693651", "direction": "0", "dep_dt": "1452693766", "route_id": "Red", "dwell_time_sec": "115"}, {"arr_dt": "1452693944", "direction": "0", "dep_dt": "1452694090", "route_id": "Red", "dwell_time_sec": "146"}, {"arr_dt": "1452694163", "direction": "0", "dep_dt": "1452694259", "route_id": "Red", "dwell_time_sec": "96"}, {"arr_dt": "1452694822", "direction": "0", "dep_dt": "1452694941", "route_id": "Red", "dwell_time_sec": "119"}, {"arr_dt": "1452695212", "direction": "0", "dep_dt": "1452695326", "route_id": "Red", "dwell_time_sec": "114"}, {"arr_dt": "1452695422", "direction": "0", "dep_dt": "1452695513", "route_id": "Red", "dwell_time_sec": "91"}, {"arr_dt": "1452695636", "direction": "0", "dep_dt": "1452695719", "route_id": "Red", "dwell_time_sec": "83"}, {"arr_dt": "1452695820", "direction": "0", "dep_dt": "1452695911", "route_id": "Red", "dwell_time_sec": "91"}, {"arr_dt": "1452696002", "direction": "0", "dep_dt": "1452696082", "route_id": "Red", "dwell_time_sec": "80"}, {"arr_dt": "1452696248", "direction": "0", "dep_dt": "1452696321", "route_id": "Red", "dwell_time_sec": "73"}, {"arr_dt": "1452696586", "direction": "0", "dep_dt": "1452696661", "route_id": "Red", "dwell_time_sec": "75"}, {"arr_dt": "1452696744", "direction": "0", "dep_dt": "1452696849", "route_id": "Red", "dwell_time_sec": "105"}, {"arr_dt": "1452696936", "direction": "0", "dep_dt": "1452697002", "route_id": "Red", "dwell_time_sec": "66"}, {"arr_dt": "1452697153", "direction": "0", "dep_dt": "1452697277", "route_id": "Red", "dwell_time_sec": "124"}, {"arr_dt": "1452697393", "direction": "0", "dep_dt": "1452697455", "route_id": "Red", "dwell_time_sec": "62"}, {"arr_dt": "1452697590", "direction": "0", "dep_dt": "1452697666", "route_id": "Red", "dwell_time_sec": "76"}, {"arr_dt": "1452697772", "direction": "0", "dep_dt": "1452697834", "route_id": "Red", "dwell_time_sec": "62"}, {"arr_dt": "1452697942", "direction": "0", "dep_dt": "1452698002", "route_id": "Red", "dwell_time_sec": "60"}, {"arr_dt": "1452698256", "direction": "0", "dep_dt": "1452698338", "route_id": "Red", "dwell_time_sec": "82"}, {"arr_dt": "1452698439", "direction": "0", "dep_dt": "1452698523", "route_id": "Red", "dwell_time_sec": "84"}, {"arr_dt": "1452698776", "direction": "0", "dep_dt": "1452698854", "route_id": "Red", "dwell_time_sec": "78"}, {"arr_dt": "1452698954", "direction": "0", "dep_dt": "1452699026", "route_id": "Red", "dwell_time_sec": "72"}, {"arr_dt": "1452699127", "direction": "0", "dep_dt": "1452699194", "route_id": "Red", "dwell_time_sec": "67"}, {"arr_dt": "1452699458", "direction": "0", "dep_dt": "1452699526", "route_id": "Red", "dwell_time_sec": "68"}, {"arr_dt": "1452699697", "direction": "0", "dep_dt": "1452699751", "route_id": "Red", "dwell_time_sec": "54"}, {"arr_dt": "1452700024", "direction": "0", "dep_dt": "1452700084", "route_id": "Red", "dwell_time_sec": "60"}, {"arr_dt": "1452700312", "direction": "0", "dep_dt": "1452700369", "route_id": "Red", "dwell_time_sec": "57"}, {"arr_dt": "1452700754", "direction": "0", "dep_dt": "1452700837", "route_id": "Red", "dwell_time_sec": "83"}, {"arr_dt": "1452700915", "direction": "0", "dep_dt": "1452700985", "route_id": "Red", "dwell_time_sec": "70"}, {"arr_dt": "1452701326", "direction": "0", "dep_dt": "1452701410", "route_id": "Red", "dwell_time_sec": "84"}, {"arr_dt": "1452702008", "direction": "0", "dep_dt": "1452702079", "route_id": "Red", "dwell_time_sec": "71"}, {"arr_dt": "1452702636", "direction": "0", "dep_dt": "1452702703", "route_id": "Red", "dwell_time_sec": "67"}, {"arr_dt": "1452703274", "direction": "0", "dep_dt": "1452703345", "route_id": "Red", "dwell_time_sec": "71"}, {"arr_dt": "1452703767", "direction": "0", "dep_dt": "1452703828", "route_id": "Red", "dwell_time_sec": "61"}, {"arr_dt": "1452703930", "direction": "0", "dep_dt": "1452703984", "route_id": "Red", "dwell_time_sec": "54"}, {"arr_dt": "1452704192", "direction": "0", "dep_dt": "1452704258", "route_id": "Red", "dwell_time_sec": "66"}, {"arr_dt": "1452704371", "direction": "0", "dep_dt": "1452704448", "route_id": "Red", "dwell_time_sec": "77"}, {"arr_dt": "1452704847", "direction": "0", "dep_dt": "1452704926", "route_id": "Red", "dwell_time_sec": "79"}, {"arr_dt": "1452705158", "direction": "0", "dep_dt": "1452705215", "route_id": "Red", "dwell_time_sec": "57"}, {"arr_dt": "1452705550", "direction": "0", "dep_dt": "1452705626", "route_id": "Red", "dwell_time_sec": "76"}, {"arr_dt": "1452705837", "direction": "0", "dep_dt": "1452705893", "route_id": "Red", "dwell_time_sec": "56"}, {"arr_dt": "1452706193", "direction": "0", "dep_dt": "1452706257", "route_id": "Red", "dwell_time_sec": "64"}, {"arr_dt": "1452706589", "direction": "0", "dep_dt": "1452706655", "route_id": "Red", "dwell_time_sec": "66"}, {"arr_dt": "1452707020", "direction": "0", "dep_dt": "1452707095", "route_id": "Red", "dwell_time_sec": "75"}, {"arr_dt": "1452707568", "direction": "0", "dep_dt": "1452707642", "route_id": "Red", "dwell_time_sec": "74"}, {"arr_dt": "1452707867", "direction": "0", "dep_dt": "1452708018", "route_id": "Red", "dwell_time_sec": "151"}, {"arr_dt": "1452708139", "direction": "0", "dep_dt": "1452708199", "route_id": "Red", "dwell_time_sec": "60"}, {"arr_dt": "1452708941", "direction": "0", "dep_dt": "1452709018", "route_id": "Red", "dwell_time_sec": "77"}, {"arr_dt": "1452709314", "direction": "0", "dep_dt": "1452709395", "route_id": "Red", "dwell_time_sec": "81"}, {"arr_dt": "1452710033", "direction": "0", "dep_dt": "1452710109", "route_id": "Red", "dwell_time_sec": "76"}, {"arr_dt": "1452710221", "direction": "0", "dep_dt": "1452710293", "route_id": "Red", "dwell_time_sec": "72"}, {"arr_dt": "1452710550", "direction": "0", "dep_dt": "1452710626", "route_id": "Red", "dwell_time_sec": "76"}, {"arr_dt": "1452710816", "direction": "0", "dep_dt": "1452710877", "route_id": "Red", "dwell_time_sec": "61"}, {"arr_dt": "1452711230", "direction": "0", "dep_dt": "1452711294", "route_id": "Red", "dwell_time_sec": "64"}, {"arr_dt": "1452711496", "direction": "0", "dep_dt": "1452711558", "route_id": "Red", "dwell_time_sec": "62"}, {"arr_dt": "1452711990", "direction": "0", "dep_dt": "1452712056", "route_id": "Red", "dwell_time_sec": "66"}, {"arr_dt": "1452712330", "direction": "0", "dep_dt": "1452712395", "route_id": "Red", "dwell_time_sec": "65"}, {"arr_dt": "1452712693", "direction": "0", "dep_dt": "1452712759", "route_id": "Red", "dwell_time_sec": "66"}, {"arr_dt": "1452713258", "direction": "0", "dep_dt": "1452713347", "route_id": "Red", "dwell_time_sec": "89"}, {"arr_dt": "1452713825", "direction": "0", "dep_dt": "1452713923", "route_id": "Red", "dwell_time_sec": "98"}, {"arr_dt": "1452714395", "direction": "0", "dep_dt": "1452714465", "route_id": "Red", "dwell_time_sec": "70"}, {"arr_dt": "1452714804", "direction": "0", "dep_dt": "1452714876", "route_id": "Red", "dwell_time_sec": "72"}, {"arr_dt": "1452715325", "direction": "0", "dep_dt": "1452715408", "route_id": "Red", "dwell_time_sec": "83"}, {"arr_dt": "1452715945", "direction": "0", "dep_dt": "1452716029", "route_id": "Red", "dwell_time_sec": "84"}, {"arr_dt": "1452716762", "direction": "0", "dep_dt": "1452716909", "route_id": "Red", "dwell_time_sec": "147"}, {"arr_dt": "1452716988", "direction": "0", "dep_dt": "1452717076", "route_id": "Red", "dwell_time_sec": "88"}, {"arr_dt": "1452717265", "direction": "0", "dep_dt": "1452717351", "route_id": "Red", "dwell_time_sec": "86"}, {"arr_dt": "1452717528", "direction": "0", "dep_dt": "1452717625", "route_id": "Red", "dwell_time_sec": "97"}, {"arr_dt": "1452717707", "direction": "0", "dep_dt": "1452717791", "route_id": "Red", "dwell_time_sec": "84"}, {"arr_dt": "1452717973", "direction": "0", "dep_dt": "1452718048", "route_id": "Red", "dwell_time_sec": "75"}, {"arr_dt": "1452718317", "direction": "0", "dep_dt": "1452718420", "route_id": "Red", "dwell_time_sec": "103"}, {"arr_dt": "1452718615", "direction": "0", "dep_dt": "1452718732", "route_id": "Red", "dwell_time_sec": "117"}, {"arr_dt": "1452718852", "direction": "0", "dep_dt": "1452718926", "route_id": "Red", "dwell_time_sec": "74"}, {"arr_dt": "1452719395", "direction": "0", "dep_dt": "1452719503", "route_id": "Red", "dwell_time_sec": "108"}, {"arr_dt": "1452719603", "direction": "0", "dep_dt": "1452719692", "route_id": "Red", "dwell_time_sec": "89"}, {"arr_dt": "1452719833", "direction": "0", "dep_dt": "1452719923", "route_id": "Red", "dwell_time_sec": "90"}, {"arr_dt": "1452720132", "direction": "0", "dep_dt": "1452720232", "route_id": "Red", "dwell_time_sec": "100"}, {"arr_dt": "1452720534", "direction": "0", "dep_dt": "1452720627", "route_id": "Red", "dwell_time_sec": "93"}, {"arr_dt": "1452720779", "direction": "0", "dep_dt": "1452720859", "route_id": "Red", "dwell_time_sec": "80"}, {"arr_dt": "1452720982", "direction": "0", "dep_dt": "1452721059", "route_id": "Red", "dwell_time_sec": "77"}, {"arr_dt": "1452721251", "direction": "0", "dep_dt": "1452721354", "route_id": "Red", "dwell_time_sec": "103"}, {"arr_dt": "1452721684", "direction": "0", "dep_dt": "1452721781", "route_id": "Red", "dwell_time_sec": "97"}, {"arr_dt": "1452721956", "direction": "0", "dep_dt": "1452722047", "route_id": "Red", "dwell_time_sec": "91"}, {"arr_dt": "1452722363", "direction": "0", "dep_dt": "1452722466", "route_id": "Red", "dwell_time_sec": "103"}, {"arr_dt": "1452722834", "direction": "0", "dep_dt": "1452722962", "route_id": "Red", "dwell_time_sec": "128"}, {"arr_dt": "1452723084", "direction": "0", "dep_dt": "1452723200", "route_id": "Red", "dwell_time_sec": "116"}, {"arr_dt": "1452723372", "direction": "0", "dep_dt": "1452723493", "route_id": "Red", "dwell_time_sec": "121"}, {"arr_dt": "1452723586", "direction": "0", "dep_dt": "1452723681", "route_id": "Red", "dwell_time_sec": "95"}, {"arr_dt": "1452723907", "direction": "0", "dep_dt": "1452724069", "route_id": "Red", "dwell_time_sec": "162"}, {"arr_dt": "1452724177", "direction": "0", "dep_dt": "1452724294", "route_id": "Red", "dwell_time_sec": "117"}, {"arr_dt": "1452724476", "direction": "0", "dep_dt": "1452724583", "route_id": "Red", "dwell_time_sec": "107"}, {"arr_dt": "1452724716", "direction": "0", "dep_dt": "1452724823", "route_id": "Red", "dwell_time_sec": "107"}, {"arr_dt": "1452725234", "direction": "0", "dep_dt": "1452725364", "route_id": "Red", "dwell_time_sec": "130"}, {"arr_dt": "1452725536", "direction": "0", "dep_dt": "1452725627", "route_id": "Red", "dwell_time_sec": "91"}, {"arr_dt": "1452725750", "direction": "0", "dep_dt": "1452725859", "route_id": "Red", "dwell_time_sec": "109"}, {"arr_dt": "1452725963", "direction": "0", "dep_dt": "1452726051", "route_id": "Red", "dwell_time_sec": "88"}, {"arr_dt": "1452726147", "direction": "0", "dep_dt": "1452726248", "route_id": "Red", "dwell_time_sec": "101"}, {"arr_dt": "1452726532", "direction": "0", "dep_dt": "1452726639", "route_id": "Red", "dwell_time_sec": "107"}, {"arr_dt": "1452726763", "direction": "0", "dep_dt": "1452726838", "route_id": "Red", "dwell_time_sec": "75"}, {"arr_dt": "1452726944", "direction": "0", "dep_dt": "1452727032", "route_id": "Red", "dwell_time_sec": "88"}, {"arr_dt": "1452727131", "direction": "0", "dep_dt": "1452727214", "route_id": "Red", "dwell_time_sec": "83"}, {"arr_dt": "1452727323", "direction": "0", "dep_dt": "1452727409", "route_id": "Red", "dwell_time_sec": "86"}, {"arr_dt": "1452727507", "direction": "0", "dep_dt": "1452727608", "route_id": "Red", "dwell_time_sec": "101"}, {"arr_dt": "1452727791", "direction": "0", "dep_dt": "1452727894", "route_id": "Red", "dwell_time_sec": "103"}, {"arr_dt": "1452727983", "direction": "0", "dep_dt": "1452728063", "route_id": "Red", "dwell_time_sec": "80"}, {"arr_dt": "1452728363", "direction": "0", "dep_dt": "1452728461", "route_id": "Red", "dwell_time_sec": "98"}, {"arr_dt": "1452728587", "direction": "0", "dep_dt": "1452728653", "route_id": "Red", "dwell_time_sec": "66"}, {"arr_dt": "1452728865", "direction": "0", "dep_dt": "1452728953", "route_id": "Red", "dwell_time_sec": "88"}, {"arr_dt": "1452729222", "direction": "0", "dep_dt": "1452729299", "route_id": "Red", "dwell_time_sec": "77"}, {"arr_dt": "1452729415", "direction": "0", "dep_dt": "1452729518", "route_id": "Red", "dwell_time_sec": "103"}, {"arr_dt": "1452729802", "direction": "0", "dep_dt": "1452729880", "route_id": "Red", "dwell_time_sec": "78"}, {"arr_dt": "1452729979", "direction": "0", "dep_dt": "1452730058", "route_id": "Red", "dwell_time_sec": "79"}, {"arr_dt": "1452730395", "direction": "0", "dep_dt": "1452730495", "route_id": "Red", "dwell_time_sec": "100"}, {"arr_dt": "1452730598", "direction": "0", "dep_dt": "1452730694", "route_id": "Red", "dwell_time_sec": "96"}, {"arr_dt": "1452730819", "direction": "0", "dep_dt": "1452730888", "route_id": "Red", "dwell_time_sec": "69"}, {"arr_dt": "1452731173", "direction": "0", "dep_dt": "1452731267", "route_id": "Red", "dwell_time_sec": "94"}, {"arr_dt": "1452731428", "direction": "0", "dep_dt": "1452731510", "route_id": "Red", "dwell_time_sec": "82"}, {"arr_dt": "1452731621", "direction": "0", "dep_dt": "1452731864", "route_id": "Red", "dwell_time_sec": "243"}, {"arr_dt": "1452731807", "direction": "0", "dep_dt": "1452731898", "route_id": "Red", "dwell_time_sec": "91"}, {"arr_dt": "1452732003", "direction": "0", "dep_dt": "1452732108", "route_id": "Red", "dwell_time_sec": "105"}, {"arr_dt": "1452732212", "direction": "0", "dep_dt": "1452732278", "route_id": "Red", "dwell_time_sec": "66"}, {"arr_dt": "1452732518", "direction": "0", "dep_dt": "1452732591", "route_id": "Red", "dwell_time_sec": "73"}, {"arr_dt": "1452732710", "direction": "0", "dep_dt": "1452732806", "route_id": "Red", "dwell_time_sec": "96"}, {"arr_dt": "1452732887", "direction": "0", "dep_dt": "1452732967", "route_id": "Red", "dwell_time_sec": "80"}, {"arr_dt": "1452733197", "direction": "0", "dep_dt": "1452733277", "route_id": "Red", "dwell_time_sec": "80"}, {"arr_dt": "1452733600", "direction": "0", "dep_dt": "1452733698", "route_id": "Red", "dwell_time_sec": "98"}, {"arr_dt": "1452734077", "direction": "0", "dep_dt": "1452734140", "route_id": "Red", "dwell_time_sec": "63"}, {"arr_dt": "1452734506", "direction": "0", "dep_dt": "1452734608", "route_id": "Red", "dwell_time_sec": "102"}, {"arr_dt": "1452734954", "direction": "0", "dep_dt": "1452735023", "route_id": "Red", "dwell_time_sec": "69"}, {"arr_dt": "1452735204", "direction": "0", "dep_dt": "1452735264", "route_id": "Red", "dwell_time_sec": "60"}, {"arr_dt": "1452735369", "direction": "0", "dep_dt": "1452735432", "route_id": "Red", "dwell_time_sec": "63"}, {"arr_dt": "1452735766", "direction": "0", "dep_dt": "1452735830", "route_id": "Red", "dwell_time_sec": "64"}, {"arr_dt": "1452736105", "direction": "0", "dep_dt": "1452736173", "route_id": "Red", "dwell_time_sec": "68"}, {"arr_dt": "1452736343", "direction": "0", "dep_dt": "1452736418", "route_id": "Red", "dwell_time_sec": "75"}, {"arr_dt": "1452736744", "direction": "0", "dep_dt": "1452736810", "route_id": "Red", "dwell_time_sec": "66"}, {"arr_dt": "1452736955", "direction": "0", "dep_dt": "1452737048", "route_id": "Red", "dwell_time_sec": "93"}, {"arr_dt": "1452737358", "direction": "0", "dep_dt": "1452737437", "route_id": "Red", "dwell_time_sec": "79"}, {"arr_dt": "1452737631", "direction": "0", "dep_dt": "1452737757", "route_id": "Red", "dwell_time_sec": "126"}, {"arr_dt": "1452738065", "direction": "0", "dep_dt": "1452738137", "route_id": "Red", "dwell_time_sec": "72"}, {"arr_dt": "1452738252", "direction": "0", "dep_dt": "1452738317", "route_id": "Red", "dwell_time_sec": "65"}, {"arr_dt": "1452738974", "direction": "0", "dep_dt": "1452739051", "route_id": "Red", "dwell_time_sec": "77"}, {"arr_dt": "1452739253", "direction": "0", "dep_dt": "1452739313", "route_id": "Red", "dwell_time_sec": "60"}, {"arr_dt": "1452739723", "direction": "0", "dep_dt": "1452739791", "route_id": "Red", "dwell_time_sec": "68"}, {"arr_dt": "1452740074", "direction": "0", "dep_dt": "1452740144", "route_id": "Red", "dwell_time_sec": "70"}, {"arr_dt": "1452740376", "direction": "0", "dep_dt": "1452740451", "route_id": "Red", "dwell_time_sec": "75"}, {"arr_dt": "1452740694", "direction": "0", "dep_dt": "1452740752", "route_id": "Red", "dwell_time_sec": "58"}, {"arr_dt": "1452741338", "direction": "0", "dep_dt": "1452741561", "route_id": "Red", "dwell_time_sec": "223"}, {"arr_dt": "1452741527", "direction": "0", "dep_dt": "1452741599", "route_id": "Red", "dwell_time_sec": "72"}, {"arr_dt": "1452741729", "direction": "0", "dep_dt": "1452741797", "route_id": "Red", "dwell_time_sec": "68"}, {"arr_dt": "1452742160", "direction": "0", "dep_dt": "1452742247", "route_id": "Red", "dwell_time_sec": "87"}, {"arr_dt": "1452742449", "direction": "0", "dep_dt": "1452742515", "route_id": "Red", "dwell_time_sec": "66"}, {"arr_dt": "1452742748", "direction": "0", "dep_dt": "1452742814", "route_id": "Red", "dwell_time_sec": "66"}, {"arr_dt": "1452743128", "direction": "0", "dep_dt": "1452743204", "route_id": "Red", "dwell_time_sec": "76"}, {"arr_dt": "1452743319", "direction": "0", "dep_dt": "1452743393", "route_id": "Red", "dwell_time_sec": "74"}, {"arr_dt": "1452743834", "direction": "0", "dep_dt": "1452743928", "route_id": "Red", "dwell_time_sec": "94"}, {"arr_dt": "1452744025", "direction": "0", "dep_dt": "1452744128", "route_id": "Red", "dwell_time_sec": "103"}, {"arr_dt": "1452744664", "direction": "0", "dep_dt": "1452744748", "route_id": "Red", "dwell_time_sec": "84"}, {"arr_dt": "1452745012", "direction": "0", "dep_dt": "1452745078", "route_id": "Red", "dwell_time_sec": "66"}, {"arr_dt": "1452745440", "direction": "0", "dep_dt": "1452745538", "route_id": "Red", "dwell_time_sec": "98"}, {"arr_dt": "1452745723", "direction": "0", "dep_dt": "1452745783", "route_id": "Red", "dwell_time_sec": "60"}, {"arr_dt": "1452745981", "direction": "0", "dep_dt": "1452746036", "route_id": "Red", "dwell_time_sec": "55"}, {"arr_dt": "1452746565", "direction": "0", "dep_dt": "1452746626", "route_id": "Red", "dwell_time_sec": "61"}, {"arr_dt": "1452746739", "direction": "0", "dep_dt": "1452746797", "route_id": "Red", "dwell_time_sec": "58"}, {"arr_dt": "1452747133", "direction": "0", "dep_dt": "1452747217", "route_id": "Red", "dwell_time_sec": "84"}]}