{"travel_times": [{"dep_dt": "1478318173", "route_id": "Red", "arr_dt": "1478318730", "direction": "0", "travel_time_sec": "557", "benchmark_travel_time_sec": "660"}, {"dep_dt": "1478318779", "route_id": "Red", "arr_dt": "1478319384", "direction": "0", "travel_time_sec": "605", "benchmark_travel_time_sec": "660"}, {"dep_dt": "1478319086", "route_id": "Red", "arr_dt": "1478319657", "direction": "0", "travel_time_sec": "571", "benchmark_travel_time_sec": "660"}, {"dep_dt": "1478319627", "route_id": "Red", "arr_dt": "1478320189", "direction": "0", "travel_time_sec": "562", "benchmark_travel_time_sec": "660"}, {"dep_dt": "1478320279", "route_id": "Red", "arr_dt": "1478320839", "direction": "0", "travel_time_sec": "560", "benchmark_travel_time_sec": "660"}, {"dep_dt": "1478320877", "route_id": "Red", "arr_dt": "1478321889", "direction": "0", "travel_time_sec": "1012", "threshold_flag_1": "threshold_id_04", "benchmark_travel_time_sec": "660"}]}